djangotextsplitter/__init__.py
djangotextsplitter/admin.py
djangotextsplitter/apps.py
djangotextsplitter/deletes.py
djangotextsplitter/loads.py
djangotextsplitter/models.py
djangotextsplitter/newwrites.py
djangotextsplitter/overwrites.py
djangotextsplitter/tests_admin.py
djangotextsplitter/tests_deletes.py
djangotextsplitter/tests_integration.py
djangotextsplitter/tests_newwrites.py
djangotextsplitter/tests_overwrites.py
djangotextsplitter/tests_unhappy.py
djangotextsplitter/urls.py
djangotextsplitter/views.py
djangotextsplitter-1.2.1.dist-info/LICENSE.txt
djangotextsplitter-1.2.1.dist-info/METADATA
djangotextsplitter-1.2.1.dist-info/WHEEL
djangotextsplitter-1.2.1.dist-info/top_level.txt
djangotextsplitter-1.2.1.dist-info/RECORD
